udnd_probability/Basedistribution.py
udnd_probability/Binomialdistribution.py
udnd_probability/Gaussiandistribution.py
udnd_probability/__init__.py
udnd_probability-0.1.dist-info/DESCRIPTION.rst
udnd_probability-0.1.dist-info/METADATA
udnd_probability-0.1.dist-info/RECORD
udnd_probability-0.1.dist-info/WHEEL
udnd_probability-0.1.dist-info/metadata.json
udnd_probability-0.1.dist-info/top_level.txt
